provo/__init__.py
provo/idvault.py
provo/provontologygraph.py
provo/startingpointclasses.py
provo/staticfunctions.py
provo/tests/__init__.py
provo/tests/test_provenance_graph.py
provo/tests/test_rdf_output.py
provo/tests/test_starting_point_classes.py
provo/tests/test_vault.py
provo-1.1.3.dist-info/LICENSE
provo-1.1.3.dist-info/METADATA
provo-1.1.3.dist-info/WHEEL
provo-1.1.3.dist-info/top_level.txt
provo-1.1.3.dist-info/RECORD
